bufferq/__init__.py
bufferq/async_queues.py
bufferq/base.py
bufferq/errors.py
bufferq/queues.py
bufferq-0.1.2.dist-info/LICENSE
bufferq-0.1.2.dist-info/METADATA
bufferq-0.1.2.dist-info/WHEEL
bufferq-0.1.2.dist-info/RECORD
