Metadata-Version: 2.1
Name: bufferq
Version: 0.1.2
Summary: Queue Library with an improved interface.
Home-page: https://github.com/eulersIDcrisis/bufferq
License: Apache-2.0
Author: Aaron Gibson
Author-email: eulersidcrisis@yahoo.com
Requires-Python: >=3.8,<4.0
Classifier: Development Status :: 4 - Beta
Classifier: Intended Audience :: Developers
Classifier: License :: OSI Approved :: Apache Software License
Classifier: Programming Language :: Python :: 3
Classifier: Programming Language :: Python :: 3.8
Classifier: Programming Language :: Python :: 3.9
Classifier: Programming Language :: Python :: 3.10
Classifier: Programming Language :: Python :: 3.11
Classifier: Programming Language :: Python :: 3.12
Project-URL: Bug Tracker, https://github.com/eulersIDcrisis/bufferq/issues
Project-URL: Repository, https://github.com/eulersIDcrisis/bufferq
